{
  "posts": [
    {
      "id": 1,
      "title": "json-server",
      "author": "typicode"
    }
  ],
  "comments": [
    {
      "id": 1,
      "body": "some comment",
      "postId": 1
    }
  ],
  "profile": [
    {
      "name": "typicode"
    }
  ],
  "product": [
    {
      "brand": "Peter England",
      "productname": "Shirt",
      "image": "https://encrypted-tbn0.gstatic.com/shopping?q=tbn:ANd9GcT2tTyC7sphwShPpqv4B7cHY1LMwkkgmui0nELjsN0R96bkLmZS5N5oKSr29HKdG5ZeIPb_PWKZZd_ez-SNUq9pLEuj1moM1NQVEjgIkii1T9CefV9dveUnRw&usqp=CAc",
      "price": "1399",
      "offer": "40%",
      "stock": "130 stocks left",
      "size": "S, M, L, Xl, XXl",
      "id": 1
    },
    {
      "brand": "Adidas",
      "productname": "Shoe",
      "image": "url",
      "price": "1200",
      "offer": "12%",
      "stock": "18 stocks available",
      "size": "7,8,9,10",
      "id": 2
    },
    {
      "brand": "Otto",
      "productname": "Cotton Pant",
      "image": "url",
      "price": "899",
      "offer": "10%",
      "stock": "7 stock available",
      "size": "32,34,36.38,40",
      "id": 3
    }
  ]
}